contentstack/__init__.py
contentstack/asset.py
contentstack/assetquery.py
contentstack/basequery.py
contentstack/contenttype.py
contentstack/controller.py
contentstack/deep_merge_lp.py
contentstack/entry.py
contentstack/entryqueryable.py
contentstack/error_messages.py
contentstack/globalfields.py
contentstack/https_connection.py
contentstack/image_transform.py
contentstack/query.py
contentstack/stack.py
contentstack/taxonomy.py
contentstack/utility.py
contentstack/variants.py
contentstack-2.4.1.dist-info/licenses/LICENSE
contentstack-2.4.1.dist-info/METADATA
contentstack-2.4.1.dist-info/WHEEL
contentstack-2.4.1.dist-info/top_level.txt
contentstack-2.4.1.dist-info/RECORD
