Metadata-Version: 2.4
Name: Contentstack
Version: 2.4.1
Summary: Contentstack is a headless CMS with an API-first approach.
Home-page: https://github.com/contentstack/contentstack-python
Author: Contentstack
Author-email: shailesh.mishra@contentstack.com, sunil.lakshman@contentstack.com
License: MIT
Keywords: contentstack-python
Classifier: License :: OSI Approved :: MIT License
Classifier: Operating System :: OS Independent
Classifier: Intended Audience :: Developers
Classifier: Natural Language :: English
Classifier: Programming Language :: Python :: 3.6
Classifier: Programming Language :: Python :: 3.7
Classifier: Programming Language :: Python :: 3.8
Classifier: Programming Language :: Python :: 3.9
Classifier: Programming Language :: Python :: 3.10
Requires-Python: >=3.6
License-File: LICENSE
Requires-Dist: requests<3.0,>=2.20.0
Requires-Dist: python-dateutil
Dynamic: author
Dynamic: author-email
Dynamic: classifier
Dynamic: description
Dynamic: description-content-type
Dynamic: home-page
Dynamic: keywords
Dynamic: license
Dynamic: license-file
Dynamic: requires-dist
Dynamic: requires-python
Dynamic: summary
